{"Repository Identifier Authorized": null, "Repository Name Unauthorized": "US Space and Rocket Center", "State": "AL", "Latitude": null, "Parent Org (Unauthorized)": null, "St City": "Huntsville", "Language of Entry": null, "Street Address 1": "One Tranquility Base", "Street Address 2": null, "St Zip Code (5 Numbers)": "35805", "Street Address County": "Madison", "Location Type": "Unverified", "St Zip Code (4 Following Numbers)": null, "URL": "http://www.spacecamp.com/museum/", "Notes": "The archives of the US Space and Rocket Center collects historical and current materials related to missiles and the space program.  Holdings consist of approximately 500,000 manuscripts, photographs, maps, and printed items.  Dr. Wernher von Braun, Colonel Leslie A. Skinner, General Holgar N Toftoy, and General John A. Barclay are among the individuals whose activities are documented.\n\nThe U.S. Space & Rocket Center is recognized as one of the most comprehensive U.S. manned space flight hardware museums in the world.  Visitors to the U.S. Space & Rocket Center will experience Huntsville's role in the making of the moon rocket, the space race, the Apollo missions, learn about the Space Shuttle program, the International Space Station and onto the next beginnings with NASA's Constellation project.", "Longitude": null, "Name Notes": null, "Entry Recorded By": "Whitney Ray", "Source of Repository Data": "Alabama Department of Archives and History", "Repository Type": "Multiple (specify in Notes field)", "Date Entry Recorded": "2018-01-29 00:00:00", "Repository Name Authorized": null, "URL of Source of Repository Data": "http://archives.state.al.us/"}