{"Repository Identifier Authorized": null, "Repository Name Unauthorized": "Alabama Center for Traditional Culture", "State": "AL", "Latitude": null, "Parent Org (Unauthorized)": "Alabama State Council on the Arts", "St City": "Montgomery", "Language of Entry": null, "Street Address 1": "201 Monroe St", "Street Address 2": "Suite 110", "St Zip Code (5 Numbers)": "36104", "Street Address County": "Montgomery", "Location Type": "Unverified", "St Zip Code (4 Following Numbers)": null, "URL": "http://www.arts.state.al.us/traditional_culture/trad_culture.aspx", "Notes": "The Alabama Center for Traditional Culture collects archival and manuscript material related to the traditional and folk culture of the state to support its program for research and presentation of the state's folklife.  Genres collected include folk music and dance traditions (gospel, blues, old-time fiddle music, polka, and Southeast Asian); oral traditions (storytelling, oral history, and jokes); material culture (folk art, traditional crafts, and folk architecture); and folk beliefs (medicine, weather lore, and superstitions). Sound records, motion pictures, still pictures, manuscripts, and printed material appear.", "Longitude": null, "Name Notes": null, "Entry Recorded By": "Whitney Ray", "Source of Repository Data": "Alabama Department of Archives and History", "Repository Type": "Government", "Date Entry Recorded": "2018-01-29 00:00:00", "Repository Name Authorized": null, "URL of Source of Repository Data": "http://archives.state.al.us/"}