{"Repository Identifier Authorized": null, "Repository Name Unauthorized": "Brownville Historical Society", "State": "NE", "Latitude": null, "Parent Org (Unauthorized)": null, "St City": "Brownville", "Language of Entry": null, "Street Address 1": "PO Box 1", "Street Address 2": null, "St Zip Code (5 Numbers)": "68321", "Street Address County": "Nemaha", "Location Type": "Mailing Address", "St Zip Code (4 Following Numbers)": null, "URL": "www.brownvillehistoricalsociety.org", "Notes": "Several museum buildings, including the Capt. Bailey House and the Carson House which are listed", "Longitude": null, "Name Notes": null, "Entry Recorded By": "Whitney Ray", "Source of Repository Data": "Nebraska State Historical Society", "Repository Type": "Historical Society/Museum", "Date Entry Recorded": "2018-01-29 00:00:00", "Repository Name Authorized": null, "URL of Source of Repository Data": "https://history.nebraska.gov/"}