{"Repository Identifier Authorized": null, "Repository Name Unauthorized": "1696 Thomas Massey House", "State": "PA", "Latitude": null, "Parent Org (Unauthorized)": "Marple Newtown Historical Society", "St City": "Broomall", "Language of Entry": null, "Street Address 1": "P.O. Box 18", "Street Address 2": null, "St Zip Code (5 Numbers)": "19008", "Street Address County": "Delaware", "Location Type": "Mailing Address", "St Zip Code (4 Following Numbers)": null, "URL": null, "Notes": null, "Longitude": null, "Name Notes": null, "Entry Recorded By": "Whitney Ray", "Source of Repository Data": "Pennsylvania Historical and Museum Commission - Pennsylvania Museums", "Repository Type": "Historical Society/Museum", "Date Entry Recorded": "2018-02-03 00:00:00", "Repository Name Authorized": null, "URL of Source of Repository Data": null}