{"Repository Identifier Authorized": null, "Repository Name Unauthorized": "Harlansburg Station Museum of Transportation", "State": "PA", "Latitude": null, "Parent Org (Unauthorized)": null, "St City": "New Castle", "Language of Entry": null, "Street Address 1": "424 Old Route 19", "Street Address 2": null, "St Zip Code (5 Numbers)": "16101", "Street Address County": "Lawrence", "Location Type": "Unverified", "St Zip Code (4 Following Numbers)": null, "URL": "http://www.harlansburgstation.com/", "Notes": null, "Longitude": null, "Name Notes": null, "Entry Recorded By": "Whitney Ray", "Source of Repository Data": "Pennsylvania Historical and Museum Commission - Pennsylvania Museums", "Repository Type": "Historical Society/Museum", "Date Entry Recorded": "2018-02-03 00:00:00", "Repository Name Authorized": null, "URL of Source of Repository Data": null}