{"Repository Identifier Authorized": null, "Repository Name Unauthorized": "Vernacular Architecture Forum", "State": "PA", "Latitude": null, "Parent Org (Unauthorized)": "Pennsylvania State University", "St City": "University Park", "Language of Entry": null, "Street Address 1": "108 Weaver Building\n", "Street Address 2": "Department of History", "St Zip Code (5 Numbers)": "16802", "Street Address County": "Centre", "Location Type": "Unverified", "St Zip Code (4 Following Numbers)": "5500", "URL": null, "Notes": null, "Longitude": null, "Name Notes": null, "Entry Recorded By": "Whitney Ray", "Source of Repository Data": "Pennsylvania Historical and Museum Commission", "Repository Type": "College/University", "Date Entry Recorded": "2018-02-02 00:00:00", "Repository Name Authorized": null, "URL of Source of Repository Data": null}