{"Repository Identifier Authorized": null, "Repository Name Unauthorized": "Warren County Historical Society", "State": "PA", "Latitude": null, "Parent Org (Unauthorized)": null, "St City": "Warren", "Language of Entry": null, "Street Address 1": "210 4th Ave.", "Street Address 2": null, "St Zip Code (5 Numbers)": "16365", "Street Address County": "Warren", "Location Type": "Unverified", "St Zip Code (4 Following Numbers)": "0427", "URL": "www.warrenhistory.org", "Notes": null, "Longitude": null, "Name Notes": null, "Entry Recorded By": "Whitney Ray", "Source of Repository Data": "Pennsylvania Historical and Museum Commission", "Repository Type": "Historical Society/Museum", "Date Entry Recorded": "2018-02-02 00:00:00", "Repository Name Authorized": null, "URL of Source of Repository Data": null}