{"Repository Identifier Authorized": null, "Repository Name Unauthorized": "Adler Planetarium And Astronomy Museum", "State": "IL", "Latitude": null, "Parent Org (Unauthorized)": null, "St City": "Chicago", "Language of Entry": null, "Street Address 1": "1300 South Lake Shore Drive", "Street Address 2": null, "St Zip Code (5 Numbers)": "60605", "Street Address County": "Cook", "Location Type": "Unverified", "St Zip Code (4 Following Numbers)": null, "URL": "http://www.adlerplanetarium.org/collections/", "Notes": "The Adler Planetarium Institutional Archives, primarily unprocessed, cover 1930-present. The Research Center also houses books, a manuscript collection, and a photographic archive of 2,500 photos. All materials pertain to the history of astronomy and rela", "Longitude": null, "Name Notes": null, "Entry Recorded By": "Whitney Ray", "Source of Repository Data": "Illinois State Historical Records Advisory Board", "Repository Type": "Historical Society/Museum", "Date Entry Recorded": "2018-04-04 00:00:00", "Repository Name Authorized": null, "URL of Source of Repository Data": null}