{"Repository Identifier Authorized": null, "Repository Name Unauthorized": "Principia College Archives", "State": "IL", "Latitude": null, "Parent Org (Unauthorized)": null, "St City": "Elsah", "Language of Entry": null, "Street Address 1": "1 Maybeck Place", "Street Address 2": null, "St Zip Code (5 Numbers)": "62028", "Street Address County": "Jersey", "Location Type": "Unverified", "St Zip Code (4 Following Numbers)": "9799", "URL": "http://www.principia.edu/archives", "Notes": "In addition to the institutional archives, the Archives also holds the\n\u2022 Alumni Book Collection\u2014books written by Principia faculty, staff, and alumni.\n\u2022 Edwins S. Leonard Jr. papers\u2014materials and drafts of the history of Principia written by Edwin S.", "Longitude": null, "Name Notes": null, "Entry Recorded By": "Whitney Ray", "Source of Repository Data": "Illinois State Historical Records Advisory Board", "Repository Type": "College/University", "Date Entry Recorded": "2018-04-04 00:00:00", "Repository Name Authorized": null, "URL of Source of Repository Data": null}