{"Repository Identifier Authorized": null, "Repository Name Unauthorized": "Peoria Public Library", "State": "IL", "Latitude": null, "Parent Org (Unauthorized)": null, "St City": "Peoria", "Language of Entry": null, "Street Address 1": "107 Ne Monroe", "Street Address 2": null, "St Zip Code (5 Numbers)": "61602", "Street Address County": "Peoria", "Location Type": "Unverified", "St Zip Code (4 Following Numbers)": "1070", "URL": "http://www.peoriapubliclibrary.org/local-history-and-genealogy", "Notes": "Local history and genealogical collection.", "Longitude": null, "Name Notes": null, "Entry Recorded By": "Whitney Ray", "Source of Repository Data": "Illinois State Historical Records Advisory Board", "Repository Type": "Public Library", "Date Entry Recorded": "2018-04-04 00:00:00", "Repository Name Authorized": null, "URL of Source of Repository Data": null}