{"Repository Identifier Authorized": null, "Repository Name Unauthorized": "Breckenridge Aviation Museum", "State": "TX", "Latitude": 32.7201397, "Parent Org (Unauthorized)": null, "St City": "Breckenridge", "Language of Entry": null, "Street Address 1": null, "Street Address 2": "Stephens County Airport", "St Zip Code (5 Numbers)": "76424", "Street Address County": "Stephens", "Location Type": "Unverified", "St Zip Code (4 Following Numbers)": null, "URL": null, "Notes": null, "Longitude": -98.8921152, "Name Notes": null, "Entry Recorded By": "Whitney Ray", "Source of Repository Data": "Texas Historical Records Advisory Board", "Repository Type": "Historical Society/Museum", "Date Entry Recorded": "2018-02-01 00:00:00", "Repository Name Authorized": null, "URL of Source of Repository Data": null}