{"Repository Identifier Authorized": null, "Repository Name Unauthorized": "James Madison University", "State": "VA", "Latitude": null, "Parent Org (Unauthorized)": null, "St City": "Harrisonburg", "Language of Entry": null, "Street Address 1": "800 S. Main St.", "Street Address 2": "Room 203, MSC 1704", "St Zip Code (5 Numbers)": "22807", "Street Address County": null, "Location Type": "Unverified", "St Zip Code (4 Following Numbers)": null, "URL": "http://www.lib.jmu.edu/special/", "Notes": "The Special Collections of JMU Libraries hold numerous historic manuscripts from local families, scholars, and businesses, as well as from various divisions of JMU itself.", "Longitude": null, "Name Notes": "Carrier Library", "Entry Recorded By": "Whitney Ray", "Source of Repository Data": "SAA@CUA", "Repository Type": "College/University", "Date Entry Recorded": "2018-03-04 00:00:00", "Repository Name Authorized": null, "URL of Source of Repository Data": "https://saaatcua.wordpress.com/map/"}