{"Repository Identifier Authorized": null, "Repository Name Unauthorized": "Chambers County Library System", "State": "TX", "Latitude": null, "Parent Org (Unauthorized)": null, "St City": "Anahuac", "Language of Entry": null, "Street Address 1": "PO Box 520", "Street Address 2": null, "St Zip Code (5 Numbers)": "77514", "Street Address County": null, "Location Type": "Mailing Address", "St Zip Code (4 Following Numbers)": null, "URL": "http://www.chambers.lib.tx.us/services.php#genealogy", "Notes": null, "Longitude": null, "Name Notes": null, "Entry Recorded By": "Eira Tansey", "Source of Repository Data": "OCLC ArchiveGrid", "Repository Type": "Public Library", "Date Entry Recorded": "2018-06-08 00:00:00", "Repository Name Authorized": null, "URL of Source of Repository Data": null}