{"Repository Identifier Authorized": null, "Repository Name Unauthorized": "University Club of New York Library", "State": "NY", "Latitude": null, "Parent Org (Unauthorized)": null, "St City": "New York", "Language of Entry": "English", "Street Address 1": "1 W 54th St", "Street Address 2": null, "St Zip Code (5 Numbers)": 10019, "Street Address County": null, "Location Type": "Unverified", "St Zip Code (4 Following Numbers)": null, "URL": "http://www.universityclubny.org/Default.aspx?p=DynamicModule&#038;pageid=291652&#038;ssid=171851&#038;vnf=1", "Notes": null, "Longitude": null, "Name Notes": null, "Entry Recorded By": "Eira Tansey", "Source of Repository Data": "OCLC ArchiveGrid", "Repository Type": "Corporation", "Date Entry Recorded": "2018-08-02 00:00:00", "Repository Name Authorized": null, "URL of Source of Repository Data": null}