{"Repository Identifier Authorized": null, "Repository Name Unauthorized": "American Pomeroy Historic Genealogical Association (APHGA)", "State": "NY", "Latitude": null, "Parent Org (Unauthorized)": null, "St City": "Syracuse", "Language of Entry": "English", "Street Address 1": "492 E. Brighton Ave.", "Street Address 2": null, "St Zip Code (5 Numbers)": 13210, "Street Address County": null, "Location Type": "Unverified", "St Zip Code (4 Following Numbers)": null, "URL": null, "Notes": null, "Longitude": null, "Name Notes": null, "Entry Recorded By": "Eira Tansey", "Source of Repository Data": "Mid-Atlantic Regional Archives Conference", "Repository Type": "Corporation", "Date Entry Recorded": "2018-07-31 00:00:00", "Repository Name Authorized": null, "URL of Source of Repository Data": null}