{"Repository Identifier Authorized": null, "Repository Name Unauthorized": "Pachuta Public Library", "State": "MS", "Latitude": null, "Parent Org (Unauthorized)": "East Mississippi Regional Library System", "St City": "Pachuta ", "Language of Entry": null, "Street Address 1": "P. O. Box 189", "Street Address 2": null, "St Zip Code (5 Numbers)": "39347", "Street Address County": "Desoto", "Location Type": "Mailing Address", "St Zip Code (4 Following Numbers)": null, "URL": "emrl.lib.ms.us/branches/pachuta-public-library", "Notes": null, "Longitude": null, "Name Notes": null, "Entry Recorded By": "Whitney Ray", "Source of Repository Data": "Society of Mississippi Archivists", "Repository Type": "Public Library", "Date Entry Recorded": "2018-03-28 00:00:00", "Repository Name Authorized": null, "URL of Source of Repository Data": null}