{"Repository Identifier Authorized": null, "Repository Name Unauthorized": "Itawamba Community College Learning Resource Center", "State": "MS", "Latitude": null, "Parent Org (Unauthorized)": "Itawamba Community College", "St City": "Fulton", "Language of Entry": null, "Street Address 1": "602 West Hill Street", "Street Address 2": null, "St Zip Code (5 Numbers)": "38843", "Street Address County": "Jefferson", "Location Type": "Unverified", "St Zip Code (4 Following Numbers)": null, "URL": "https://www.iccms.edu/LRC", "Notes": null, "Longitude": null, "Name Notes": null, "Entry Recorded By": "Whitney Ray", "Source of Repository Data": "Society of Mississippi Archivists", "Repository Type": "College/University", "Date Entry Recorded": "2018-03-28 00:00:00", "Repository Name Authorized": null, "URL of Source of Repository Data": null}