{"Repository Identifier Authorized": null, "Repository Name Unauthorized": "Tulane University Howard-Tilton Memorial Library Louisiana Research Collection", "State": "LA", "Latitude": null, "Parent Org (Unauthorized)": "Tulane University", "St City": "New Orleans", "Language of Entry": null, "Street Address 1": "Room 202 Jones Hall", "Street Address 2": "6801 Freret Street", "St Zip Code (5 Numbers)": 70118, "Street Address County": null, "Location Type": "Reading Room", "St Zip Code (4 Following Numbers)": null, "URL": "http://larc.tulane.edu", "Notes": "Combines one of the more comprehensive research archives (with almost four linear miles of documents from the founding of the city to the present) with a major Louisiana research library, creating a unified resource for archives, books, maps, images, and ephemera. Special strengths are Carnival, Colonial Louisiana, Civil War, Ephemera, Jewish studies, Louisiana politics, medical history, social welfare, Southern literature, waterways, and women\u2019s studies.", "Longitude": null, "Name Notes": null, "Entry Recorded By": "Eira Tansey", "Source of Repository Data": "Greater New Orleans Archivists", "Repository Type": "College/University", "Date Entry Recorded": "2018-05-11 00:00:00", "Repository Name Authorized": null, "URL of Source of Repository Data": "http://www.gnoarchivists.org/directory/"}