{"Repository Identifier Authorized": null, "Repository Name Unauthorized": "Cleveland Institute of Art Archives", "State": "OH", "Latitude": null, "Parent Org (Unauthorized)": null, "St City": "Cleveland", "Language of Entry": null, "Street Address 1": "11610 Euclid Avenue", "Street Address 2": "Jessica R. Gund Memorial Library", "St Zip Code (5 Numbers)": "44106", "Street Address County": null, "Location Type": "Unverified", "St Zip Code (4 Following Numbers)": null, "URL": null, "Notes": null, "Longitude": null, "Name Notes": null, "Entry Recorded By": "Whitney Ray", "Source of Repository Data": "Cleveland Archival Roundtable", "Repository Type": "College/University", "Date Entry Recorded": "2018-02-17 00:00:00", "Repository Name Authorized": null, "URL of Source of Repository Data": null}