{"Repository Identifier Authorized": null, "Repository Name Unauthorized": "University of North Carolina at Wilmington, University Collection", "State": "NC", "Latitude": null, "Parent Org (Unauthorized)": null, "St City": "Wilmington", "Language of Entry": null, "Street Address 1": "101 Academic Support Building, 601 S College St", "Street Address 2": null, "St Zip Code (5 Numbers)": "28409", "Street Address County": null, "Location Type": "Unverified", "St Zip Code (4 Following Numbers)": 7439, "URL": "www.uncwil.edu/mwc/", "Notes": "Museum and Public College/University. This repository has been identified as a cultural heritage institution through NC ECHO.", "Longitude": null, "Name Notes": "Museum of World Cultures", "Entry Recorded By": "Whitney Ray", "Source of Repository Data": "North Carolina Digital Heritage Center", "Repository Type": "Multiple (specify in Notes field)", "Date Entry Recorded": "2018-01-20 00:00:00", "Repository Name Authorized": null, "URL of Source of Repository Data": null}