{"Repository Identifier Authorized": null, "Repository Name Unauthorized": "Los Angeles Philharmonic Archives", "State": "CA", "Latitude": 34.0551838855, "Parent Org (Unauthorized)": null, "St City": "Los Angeles", "Language of Entry": null, "Street Address 1": "151 South Grand Avenue ", "Street Address 2": null, "St Zip Code (5 Numbers)": "90012", "Street Address County": null, "Location Type": "Unverified", "St Zip Code (4 Following Numbers)": "3034", "URL": "http://www.laphil.com/philpedia/archives.cfm", "Notes": null, "Longitude": -118.249669075, "Name Notes": null, "Entry Recorded By": "Whitney Ray", "Source of Repository Data": "Online Archive of California", "Repository Type": "Corporation", "Date Entry Recorded": "2018-04-04 00:00:00", "Repository Name Authorized": null, "URL of Source of Repository Data": null}