{"Repository Identifier Authorized": null, "Repository Name Unauthorized": "Richard Nixon Presidential Library and Museum", "State": "CA", "Latitude": 33.889120625, "Parent Org (Unauthorized)": null, "St City": "Yorba Linda", "Language of Entry": null, "Street Address 1": "18001 Yorba Linda Blvd.", "Street Address 2": null, "St Zip Code (5 Numbers)": "92886", "Street Address County": null, "Location Type": "Unverified", "St Zip Code (4 Following Numbers)": null, "URL": "http://nixonlibrary.gov/", "Notes": null, "Longitude": -117.819314003, "Name Notes": null, "Entry Recorded By": "Whitney Ray", "Source of Repository Data": "Online Archive of California", "Repository Type": "Government", "Date Entry Recorded": "2018-04-04 00:00:00", "Repository Name Authorized": null, "URL of Source of Repository Data": null}