{"Repository Identifier Authorized": null, "Repository Name Unauthorized": "Minnesota Air National Guard Foundation", "State": "MN", "Latitude": null, "Parent Org (Unauthorized)": null, "St City": "St. Paul", "Language of Entry": null, "Street Address 1": "670 General Miller Drive", "Street Address 2": "Minneapolis-St. Paul International Airport", "St Zip Code (5 Numbers)": "55111", "Street Address County": null, "Location Type": "Unverified", "St Zip Code (4 Following Numbers)": null, "URL": null, "Notes": null, "Longitude": null, "Name Notes": null, "Entry Recorded By": "Whitney Ray", "Source of Repository Data": "Minnesota Historical Society", "Repository Type": "Historical Society/Museum", "Date Entry Recorded": "2018-03-15 00:00:00", "Repository Name Authorized": null, "URL of Source of Repository Data": null}