{"Repository Identifier Authorized": null, "Repository Name Unauthorized": "Paulding County Historical Society", "State": "GA", "Latitude": null, "Parent Org (Unauthorized)": null, "St City": "Dallas", "Language of Entry": null, "Street Address 1": "295 North Johnston St.", "Street Address 2": null, "St Zip Code (5 Numbers)": "30132", "Street Address County": "Paulding", "Location Type": "Unverified", "St Zip Code (4 Following Numbers)": null, "URL": "http://www.pchsm.org", "Notes": "Photographs; war room artifacts; decade room with various artifacts; school room; kitchen with wood stove, ice box and other artifacts; American Indian artifacts; research room with donated family histories and other historical genealogy records.", "Longitude": null, "Name Notes": "Paulding County Museum", "Entry Recorded By": "Whitney Ray", "Source of Repository Data": "Georgia Historical Records Advisory Council", "Repository Type": "Historical Society/Museum", "Date Entry Recorded": "2018-03-10 00:00:00", "Repository Name Authorized": null, "URL of Source of Repository Data": null}