{"Repository Identifier Authorized": null, "Repository Name Unauthorized": "Cannonball House  ", "State": "GA", "Latitude": null, "Parent Org (Unauthorized)": "Friends of the Cannonball House, Inc.", "St City": "Macon", "Language of Entry": null, "Street Address 1": "856 Mulberry Street            ", "Street Address 2": null, "St Zip Code (5 Numbers)": "31201", "Street Address County": "Bibb", "Location Type": "Unverified", "St Zip Code (4 Following Numbers)": null, "URL": "http://www.cannonballhouse.org/", "Notes": "This southern home, c. 1853, is named for damage sustained during the Civil War.  Listed on the National Register of Historic Places, it is an example of authentic Greek Revival architecture containing fine period furnishings.  The house is also the repository for the Founders' parlor societies, recreated from Wesleyan College, where they began in 1851 and 1852.A Civil War military collection features officers' uniforms, company flags, swords, and guns used by Georgians during the War Between the States.", "Longitude": null, "Name Notes": null, "Entry Recorded By": "Whitney Ray", "Source of Repository Data": "Georgia Historical Records Advisory Council", "Repository Type": "Historical Society/Museum", "Date Entry Recorded": "2018-03-10 00:00:00", "Repository Name Authorized": null, "URL of Source of Repository Data": null}