{"Repository Identifier Authorized": null, "Repository Name Unauthorized": "East Georgia Genealogical Society", "State": "GA", "Latitude": null, "Parent Org (Unauthorized)": null, "St City": "Winder", "Language of Entry": null, "Street Address 1": "P. O. Box 117", "Street Address 2": null, "St Zip Code (5 Numbers)": "30680", "Street Address County": "Barrow", "Location Type": "Mailing Address", "St Zip Code (4 Following Numbers)": null, "URL": "http://www.rootsweb.com/~gaeggs/", "Notes": "Genealogical books for the following families: Bramlett, Dunagan, Elder, Grubb, Harrison, William L., Kelley, Henry S. Leach, McClung, McGehee, Woodall, William H. Potter, Teagle and Andrew and Joel Wages; ancestor charts, obituaries for Barrow and Walton counties,  and periodicals.  Published the following books: Barrow County Georgia Cemeteries; Walton County Georgia Cemeteries; Jackson County Georgia Marriages, 1805-1910; Barrow County Marriages, 1915-1932; East Georgia Settlers - Family Sketches.", "Longitude": null, "Name Notes": null, "Entry Recorded By": "Whitney Ray", "Source of Repository Data": "Georgia Historical Records Advisory Council", "Repository Type": "Historical Society/Museum", "Date Entry Recorded": "2018-03-10 00:00:00", "Repository Name Authorized": null, "URL of Source of Repository Data": null}