{"Repository Identifier Authorized": null, "Repository Name Unauthorized": "Vizcaya Museum and Gardens Archives", "State": "FL", "Latitude": null, "Parent Org (Unauthorized)": null, "St City": "Miami", "Language of Entry": null, "Street Address 1": "3251 South Miami Avenue", "Street Address 2": null, "St Zip Code (5 Numbers)": "33129", "Street Address County": "Miami-Dade ", "Location Type": "Unverified", "St Zip Code (4 Following Numbers)": null, "URL": "http://vizcaya.org/", "Notes": " Archives maintains over 2,600 Architectural drawings, 2,400 photographs, correspondence and financial records created by James Deering and his associates during the design, planning and building of Vizcaya from 1910 to 1925. As the result of a two and a half year massive organizing and cataloging ,conservation and preservation project the materials the majority of these materials have been digitized Also has administrative records associated with past museum directors, curators and departmental staff. ", "Longitude": null, "Name Notes": null, "Entry Recorded By": "Whitney Ray", "Source of Repository Data": "University of Central Florida", "Repository Type": "Historical Society/Museum", "Date Entry Recorded": "2018-03-21 00:00:00", "Repository Name Authorized": null, "URL of Source of Repository Data": null}